lxdbapi/__init__.py
lxdbapi/errors.py
lxdbapi/sqlalchemy_leanxcale.py
lxdbapi-2.7.202509241259.dist-info/LICENSE
lxdbapi-2.7.202509241259.dist-info/METADATA
lxdbapi-2.7.202509241259.dist-info/WHEEL
lxdbapi-2.7.202509241259.dist-info/entry_points.txt
lxdbapi-2.7.202509241259.dist-info/top_level.txt
lxdbapi-2.7.202509241259.dist-info/RECORD
