Metadata-Version: 2.1
Name: lxdbapi
Version: 2.7.202509241259
Summary: LeanXcale implementation for Python Database API Specification v2.0
Author-email: leanXcale <support@leanxcale.com>
License: Copyright <2023> <LEANXCALE S.L.>
Project-URL: Homepage, http://leanxcale.com
Classifier: Programming Language :: Python :: 3
Classifier: Operating System :: OS Independent
Requires-Python: >=3.7
License-File: LICENSE
